{
  "pratos": [
    {
      "id": "d98f",
      "nome": "Salada Caesar",
      "categoria": "Entrada",
      "preco": 25,
      "tempo_preparo": 10
    },
    {
      "id": "f89d",
      "nome": "Bife à Parmegiana",
      "categoria": "Prato Principal",
      "preco": 45.5,
      "tempo_preparo": 30
    },
    {
      "id": "af2a",
      "nome": "Pudim de Leite Condensado",
      "categoria": "Sobremesa",
      "preco": 9.99,
      "tempo_preparo": 120
    },
    {
      "id": "b12c",
      "nome": "Bruschetta",
      "categoria": "Entrada",
      "preco": 18,
      "tempo_preparo": 15
    },
    {
      "id": "c34d",
      "nome": "Risoto de Cogumelos",
      "categoria": "Prato Principal",
      "preco": 52,
      "tempo_preparo": 40
    },
    {
      "id": "e56f",
      "nome": "Mousse de Chocolate",
      "categoria": "Sobremesa",
      "preco": 12.5,
      "tempo_preparo": 90
    },
    {
      "id": "f78g",
      "nome": "Suco de Laranja Natural",
      "categoria": "Bebida",
      "preco": 7,
      "tempo_preparo": 5
    },
    {
      "id": "h90i",
      "nome": "Chá Gelado",
      "categoria": "Bebida",
      "preco": 6,
      "tempo_preparo": 5
    },
    {
      "id": "j23k",
      "nome": "Filé Mignon ao Molho Madeira",
      "categoria": "Prato Principal",
      "preco": 65,
      "tempo_preparo": 35
    },
    {
      "id": "l45m",
      "nome": "Salada Caprese",
      "categoria": "Entrada",
      "preco": 22,
      "tempo_preparo": 12
    },
    {
      "id": "n67o",
      "nome": "Panna Cotta",
      "categoria": "Sobremesa",
      "preco": 14,
      "tempo_preparo": 100
    },
    {
      "id": "p89q",
      "nome": "Refrigerante Lata",
      "categoria": "Bebida",
      "preco": 5,
      "tempo_preparo": 1
    },
    {
      "id": "q12r",
      "nome": "Caldinho de Feijão",
      "categoria": "Entrada",
      "preco": 12,
      "tempo_preparo": 20
    },
    {
      "id": "r34s",
      "nome": "Frango Grelhado com Ervas",
      "categoria": "Prato Principal",
      "preco": 38,
      "tempo_preparo": 25
    },
    {
      "id": "s56t",
      "nome": "Tiramisu",
      "categoria": "Sobremesa",
      "preco": 16,
      "tempo_preparo": 110
    },
    {
      "id": "t78u",
      "nome": "Água Mineral",
      "categoria": "Bebida",
      "preco": 3,
      "tempo_preparo": 1
    },
    {
      "id": "u90v",
      "nome": "Empanadas de Carne",
      "categoria": "Entrada",
      "preco": 20,
      "tempo_preparo": 18
    },
    {
      "id": "v23w",
      "nome": "Lasanha à Bolonhesa",
      "categoria": "Prato Principal",
      "preco": 50,
      "tempo_preparo": 45
    },
    {
      "id": "w45x",
      "nome": "Sorvete de Creme",
      "categoria": "Sobremesa",
      "preco": 10,
      "tempo_preparo": 30
    },
    {
      "id": "x67y",
      "nome": "Cerveja Artesanal",
      "categoria": "Bebida",
      "preco": 12,
      "tempo_preparo": 2
    },
    {
      "id": "y89z",
      "nome": "Bolinho de Bacalhau",
      "categoria": "Entrada",
      "preco": 22,
      "tempo_preparo": 22
    },
    {
      "id": "z01a",
      "nome": "Peixe ao Molho de Limão",
      "categoria": "Prato Principal",
      "preco": 55,
      "tempo_preparo": 33
    },
    {
      "id": "a23b",
      "nome": "Cheesecake de Frutas Vermelhas",
      "categoria": "Sobremesa",
      "preco": 18,
      "tempo_preparo": 90
    },
    {
      "id": "b45c",
      "nome": "Refrigerante Zero",
      "categoria": "Bebida",
      "preco": 5,
      "tempo_preparo": 1
    },
    {
      "id": "c67d",
      "nome": "Camarão Empanado",
      "categoria": "Entrada",
      "preco": 28,
      "tempo_preparo": 20
    },
    {
      "id": "d89e",
      "nome": "Espaguete Carbonara",
      "categoria": "Prato Principal",
      "preco": 42,
      "tempo_preparo": 28
    },
    {
      "id": "e01f",
      "nome": "Brownie com Sorvete",
      "categoria": "Sobremesa",
      "preco": 15,
      "tempo_preparo": 60
    },
    {
      "id": "f23g",
      "nome": "Suco Verde Detox",
      "categoria": "Bebida",
      "preco": 8,
      "tempo_preparo": 5
    },
    {
      "id": "g45h",
      "nome": "Espetinho de Carne",
      "categoria": "Entrada",
      "preco": 17,
      "tempo_preparo": 18
    },
    {
      "id": "h67i",
      "nome": "Frango à Kiev",
      "categoria": "Prato Principal",
      "preco": 48,
      "tempo_preparo": 40
    },
    {
      "id": "i89j",
      "nome": "Pavê de Chocolate",
      "categoria": "Sobremesa",
      "preco": 13,
      "tempo_preparo": 80
    },
    {
      "id": "j01k",
      "nome": "Cappuccino",
      "categoria": "Bebida",
      "preco": 7,
      "tempo_preparo": 5
    },
    {
      "id": "k11l",
      "nome": "Calabresa Acebolada",
      "categoria": "Entrada",
      "preco": 19,
      "tempo_preparo": 15
    },
    {
      "id": "l22m",
      "nome": "Bacalhau à Gomes de Sá",
      "categoria": "Prato Principal",
      "preco": 60,
      "tempo_preparo": 50
    },
    {
      "id": "m33n",
      "nome": "Cheesecake de Limão",
      "categoria": "Sobremesa",
      "preco": 17,
      "tempo_preparo": 95
    },
    {
      "id": "n44o",
      "nome": "Suco de Abacaxi com Hortelã",
      "categoria": "Bebida",
      "preco": 7,
      "tempo_preparo": 4
    },
    {
      "id": "o55p",
      "nome": "Salada de Quinoa",
      "categoria": "Entrada",
      "preco": 23,
      "tempo_preparo": 12
    },
    {
      "id": "p66q",
      "nome": "Costela ao Barbecue",
      "categoria": "Prato Principal",
      "preco": 70,
      "tempo_preparo": 60
    },
    {
      "id": "e068",
      "nome": "Polpeta",
      "categoria": "Prato Principal",
      "tempo_preparo": 60,
      "preco": 24.99
    },
    {
      "id": "e06c",
      "nome": "Strogonoff de Carne",
      "categoria": "Prato Principal",
      "tempo_preparo": 90,
      "preco": 49.99
    },
    {
      "id": "5f94",
      "nome": "Bife a Cavalo",
      "categoria": "Prato Principal",
      "tempo_preparo": 85,
      "preco": 39.9
    },
    {
      "id": "a5ca",
      "nome": "Bife à Milanesa",
      "categoria": "Prato Principal",
      "tempo_preparo": 35,
      "preco": 49.9
    },
    {
      "id": "bce4",
      "nome": "Suco de Melancia",
      "categoria": "Bebida",
      "tempo_preparo": 5,
      "preco": 9.99
    },
    {
      "id": "e616",
      "nome": "Suco de Uva",
      "categoria": "Bebida",
      "tempo_preparo": 5,
      "preco": 7.99
    },
    {
      "id": "03f1",
      "nome": "Risoto de Camarão",
      "categoria": "Prato Principal",
      "tempo_preparo": 60,
      "preco": 117.99
    }
  ]
}